odoo/addons/account_move_print/README.rst
odoo/addons/account_move_print/__init__.py
odoo/addons/account_move_print/__manifest__.py
odoo/addons/account_move_print/i18n/account_move_print.pot
odoo/addons/account_move_print/i18n/es.po
odoo/addons/account_move_print/i18n/hr.po
odoo/addons/account_move_print/i18n/it.po
odoo/addons/account_move_print/readme/CONTRIBUTORS.rst
odoo/addons/account_move_print/readme/DESCRIPTION.rst
odoo/addons/account_move_print/readme/USAGE.rst
odoo/addons/account_move_print/report/journal_report.xml
odoo/addons/account_move_print/static/description/icon.png
odoo/addons/account_move_print/static/description/index.html
odoo14_addon_account_move_print-14.0.1.0.1.dev9.dist-info/METADATA
odoo14_addon_account_move_print-14.0.1.0.1.dev9.dist-info/WHEEL
odoo14_addon_account_move_print-14.0.1.0.1.dev9.dist-info/top_level.txt
odoo14_addon_account_move_print-14.0.1.0.1.dev9.dist-info/RECORD
